AUTHORS
LICENSE
MANIFEST.in
README.rst
setup.cfg
setup.py
Formular.egg-info/PKG-INFO
Formular.egg-info/SOURCES.txt
Formular.egg-info/dependency_links.txt
Formular.egg-info/top_level.txt
formular/__init__.py
formular/_csrf.py
formular/_utils.py
formular/datastructures.py
formular/exceptions.py
formular/fields.py
formular/forms.py
formular/validators.py
formular/widgets.py
formular/i18n/__init__.pyc
formular/i18n/messages.pot
formular/i18n/de/messages.mo
formular/i18n/de/messages.po