Metadata-Version: 1.0
Name: Formular
Version: 0.2
Summary: Formular is a library for validation of form-like data.
Home-page: http://packages.python.org/Formular
Author: Daniel Neuhäuser
Author-email: dasdasich@gmail.com
License: MIT License
Keywords: forms
Platform: any
Classifier: Intended Audience :: Developers
Classifier: License :: OSI Approved :: MIT License
Classifier: Operating System :: OS Independent
Classifier: Programming Language :: Python :: 2.6
Classifier: Topic :: Internet :: WWW/HTTP
